src/__init__.py
src/__main__.py
ownkewlpackage-0.1.0.dist-info/METADATA
ownkewlpackage-0.1.0.dist-info/WHEEL
ownkewlpackage-0.1.0.dist-info/top_level.txt
ownkewlpackage-0.1.0.dist-info/RECORD
