Metadata-Version: 2.1
Name: ownkewlpackage
Version: 0.1.0
Summary: Описание моего Python-пакета
Author-email: Your Name <youremail@example.com>
License: MIT
Requires-Python: >=3.12
Requires-Dist: requests>=2.25.1
Requires-Dist: numpy>=1.19.2
Provides-Extra: dev
Requires-Dist: pytest>=6.2.1; extra == "dev"
Requires-Dist: flake8>=3.8.4; extra == "dev"
Provides-Extra: docs
Requires-Dist: sphinx>=3.5.3; extra == "docs"
